compas_singular/__init__.py
compas_singular/algorithms/__init__.py
compas_singular/algorithms/decomposition.py
compas_singular/algorithms/isomorphism.py
compas_singular/algorithms/layout.py
compas_singular/algorithms/mapping.py
compas_singular/algorithms/propagation.py
compas_singular/algorithms/triangulation.py
compas_singular/algorithms/twocoloring.py
compas_singular/datastructures/__init__.py
compas_singular/datastructures/lizard/__init__.py
compas_singular/datastructures/lizard/lizard.py
compas_singular/datastructures/mesh/__init__.py
compas_singular/datastructures/mesh/coloring.py
compas_singular/datastructures/mesh/mesh.py
compas_singular/datastructures/mesh/operations.py
compas_singular/datastructures/mesh_quad/__init__.py
compas_singular/datastructures/mesh_quad/coloring.py
compas_singular/datastructures/mesh_quad/grammar_pattern.py
compas_singular/datastructures/mesh_quad/grammar_shape.py
compas_singular/datastructures/mesh_quad/mesh_quad.py
compas_singular/datastructures/mesh_quad/morphing.py
compas_singular/datastructures/mesh_quad/grammar/__init__.py
compas_singular/datastructures/mesh_quad/grammar/add_strip.py
compas_singular/datastructures/mesh_quad/grammar/delete_strip.py
compas_singular/datastructures/mesh_quad_coarse/__init__.py
compas_singular/datastructures/mesh_quad_coarse/coloring.py
compas_singular/datastructures/mesh_quad_coarse/mesh_quad_coarse.py
compas_singular/datastructures/mesh_quad_pseudo/__init__.py
compas_singular/datastructures/mesh_quad_pseudo/grammar_poles.py
compas_singular/datastructures/mesh_quad_pseudo/mesh_quad_pseudo.py
compas_singular/datastructures/mesh_quad_pseudo_coarse/__init__.py
compas_singular/datastructures/mesh_quad_pseudo_coarse/mesh_quad_pseudo_coarse.py
compas_singular/datastructures/network/__init__.py
compas_singular/datastructures/network/network.py
compas_singular/datastructures/skeleton/__init__.py
compas_singular/datastructures/skeleton/skeleton.py
compas_singular/geometry/__init__.py
compas_singular-0.1.5.dist-info/AUTHORS.md
compas_singular-0.1.5.dist-info/LICENSE
compas_singular-0.1.5.dist-info/METADATA
compas_singular-0.1.5.dist-info/WHEEL
compas_singular-0.1.5.dist-info/entry_points.txt
compas_singular-0.1.5.dist-info/top_level.txt
compas_singular-0.1.5.dist-info/RECORD
